{"checksum":"47DEQpj8HBSa+/TImW+5JCeuQeRkm5NMpJWZG3hSuFU=","payload":{"features":[{"description":"Estende a condição Bluetooth com pesquisa baseada no endereço e seleção do intervalo de procura","maxActionPlatform":2147483647,"maxConditionPlatform":2147483647,"minActionPlatform":0,"minConditionPlatform":0,"name":"btscanpro","packages":["plugins"],"priceType":0,"remote":"v1MmRoEwJkHDF62U6DaE74+PWJzUyKJCLOfSWUgfcaU=","source":1,"title":"Bluetooth Pro","type":1},{"description":"Estende a condição WIFI com busca baseada no endereço e seleção do intervalo de procura","maxActionPlatform":2147483647,"maxConditionPlatform":2147483647,"minActionPlatform":0,"minConditionPlatform":0,"name":"wlanscanpro","packages":["plugins"],"priceType":0,"remote":"Pe3oGcCfgcNHrW/N1RsIXn4k+/eAWhfUr2BA5SWe6ok=","source":1,"title":"WiFi Pro","type":1},{"description":"Situação Localização com uso do melhor método de posicionamento possivel","maxActionPlatform":2147483647,"maxConditionPlatform":2147483647,"minActionPlatform":0,"minConditionPlatform":0,"name":"location","packages":["plugins"],"priceType":0,"remote":"DDK08VvZBoTp6sGIQjExoy93XRTef4IsOf0kKw9USJk=","source":1,"title":"Localização","type":1},{"description":"Situação de ligar ou desligar a tela","maxActionPlatform":2147483647,"maxConditionPlatform":2147483647,"minActionPlatform":0,"minConditionPlatform":0,"name":"display","packages":["plugins"],"priceType":0,"remote":"GaSsw7vzxX5qOSyqUfRDm20UPmi2BkYnwdP/6jPQHJg=","source":1,"title":"Tela","type":1},{"description":"GPS setting","maxActionPlatform":2147483647,"maxConditionPlatform":2147483647,"minActionPlatform":0,"minConditionPlatform":0,"name":"gps","packages":["plugins"],"priceType":0,"remote":"uRxv/SZQlu+9B1dh87pCUx1Aj96brbOCfyB+RYLaILk=","source":1,"title":"GPS","type":1},{"description":"Detect objects being close to the device","maxActionPlatform":2147483647,"maxConditionPlatform":2147483647,"minActionPlatform":0,"minConditionPlatform":0,"name":"proximity","packages":["plugins"],"priceType":0,"remote":"wL90uyyGUt7ZJNiMyiKpgPqYidPirtN9aERH5YxmHuc=","source":1,"title":"Proximity Sensor","type":1},{"description":"Alterar para uso de Dados Móveis","maxActionPlatform":2147483647,"maxConditionPlatform":2147483647,"minActionPlatform":0,"minConditionPlatform":0,"name":"mobiledata","packages":["plugins"],"priceType":0,"remote":"K0RiITGMUoDaTSVFZSeHYOO8c0ms4m5aAdXYg3wpGTI=","source":1,"title":"Dados móveis","type":16},{"description":"Alterar Rede Móvel Celular","maxActionPlatform":2147483647,"maxConditionPlatform":2147483647,"minActionPlatform":0,"minConditionPlatform":0,"name":"mobilenetwork","packages":["plugins"],"priceType":0,"remote":"258hmiLHcfnwcWxP2hWMImLHPwj+uZUysgRkpUu9N5w=","source":1,"title":"Rede móvel celular","type":16},{"description":"Alterar para modo avião","maxActionPlatform":2147483647,"maxConditionPlatform":2147483647,"minActionPlatform":0,"minConditionPlatform":0,"name":"flightmode","packages":["plugins"],"priceType":0,"remote":"2QvuibR7xHQ40N8hdF3C95ZIrOM34mzPzLEqXdf2vaE=","source":1,"title":"Modo de avião","type":16},{"description":"Seleção do toque de chamada","maxActionPlatform":2147483647,"maxConditionPlatform":2147483647,"minActionPlatform":0,"minConditionPlatform":0,"name":"ringtone","packages":["plugins"],"priceType":0,"remote":"zOBkABKmQbDD6/J1WZt2ZwXWAxgsaHj9yf5xpW7DsuM=","source":1,"title":"Toque de chamada","type":16},{"description":"Configura a vibração","maxActionPlatform":2147483647,"maxConditionPlatform":2147483647,"minActionPlatform":0,"minConditionPlatform":0,"name":"vibration","packages":["plugins"],"priceType":0,"remote":"NKQa78W2AZyFSkYnHz9bpHvMFsVNvDnF66h8x684i4U=","source":1,"title":"Vibração","type":16},{"description":"Alterador de ambiente","maxActionPlatform":2147483647,"maxConditionPlatform":2147483647,"minActionPlatform":0,"minConditionPlatform":0,"name":"ambience","packages":["plugins"],"priceType":0,"remote":"uDYbJyhtYTA/yrLt94baraqvhSa65l/9FDoBpXph3s8=","source":1,"title":"Ambiente","type":16},{"description":"Alterna o compartilhamento de Internet (hotspot)","maxActionPlatform":2147483647,"maxConditionPlatform":2147483647,"minActionPlatform":0,"minConditionPlatform":0,"name":"tethering","packages":["plugins"],"priceType":0,"remote":"Hm8QgP8WS4Rf9YItppa2BtJXlcYIh1tePgL71iCYA7s=","source":1,"title":"Compartilhamento de Internet","type":16},{"description":"Executa qualquer comando personalizado","maxActionPlatform":2147483647,"maxConditionPlatform":2147483647,"minActionPlatform":0,"minConditionPlatform":0,"name":"command","packages":["plugins"],"priceType":0,"remote":"q3BQ6xzKkl1LINjhP4jf2nGME0CxlMh91OgJziXz97s=","source":1,"title":"Comando","type":2},{"description":"Mantém o registro das mudanças de situações","maxActionPlatform":2147483647,"maxConditionPlatform":2147483647,"minActionPlatform":0,"minConditionPlatform":0,"name":"logging","packages":["plugins"],"priceType":0,"remote":"fLsHOUy6dDFmwjNOWqfKgJUcTy3kpr/a4RREm/7FGZU=","source":1,"title":"Registro","type":2},{"description":"Change watchface on your smartwatch. Compatible with Rockpool app.","maxActionPlatform":2147483647,"maxConditionPlatform":2147483647,"minActionPlatform":0,"minConditionPlatform":0,"name":"watchface","packages":["plugins"],"priceType":0,"remote":"hpGI+mZH8unON2QaOsa3QqbCLZGcWtPLODG3GV33TZc=","source":1,"title":"Watchface","type":2}],"version":194}}