{"checksum":"47DEQpj8HBSa+/TImW+5JCeuQeRkm5NMpJWZG3hSuFU=","payload":{"features":[{"description":"***","maxPlatform":2147483647,"minPlatform":0,"name":"plugins","priceType":1,"title":"获取所有插件!","type":4},{"description":"使用输入法搜索和日历选择扩展日期范围","maxActionPlatform":2147483647,"maxConditionPlatform":2147483647,"minActionPlatform":0,"minConditionPlatform":0,"name":"calendarpro","packages":["plugins"],"priceType":1,"remote":null,"source":0,"title":"Calendar Pro","type":1},{"description":"通过基于地址的搜索和扫描间隔选择扩展 WiFi 条件","maxActionPlatform":2147483647,"maxConditionPlatform":2147483647,"minActionPlatform":0,"minConditionPlatform":0,"name":"wlanscanpro","packages":["plugins"],"priceType":1,"remote":null,"source":0,"title":"WiFi Pro","type":1},{"description":"通过基于地址的搜索和扫描间隔选择扩展蓝牙条件","maxActionPlatform":2147483647,"maxConditionPlatform":2147483647,"minActionPlatform":0,"minConditionPlatform":0,"name":"btscanpro","packages":["plugins"],"priceType":1,"remote":null,"source":0,"title":"Bluetooth Pro","type":1},{"description":"显示开启/关闭状态","maxActionPlatform":2147483647,"maxConditionPlatform":2147483647,"minActionPlatform":0,"minConditionPlatform":0,"name":"display","packages":["plugins"],"priceType":1,"remote":null,"source":0,"title":"显示","type":1},{"description":"使用 NFC 标签切换状态","maxActionPlatform":2147483647,"maxConditionPlatform":2147483647,"minActionPlatform":0,"minConditionPlatform":0,"name":"nfc","packages":["plugins"],"priceType":1,"remote":null,"source":0,"title":"NFC 标签","type":1},{"description":"NFC 设置","maxActionPlatform":2147483647,"maxConditionPlatform":2147483647,"minActionPlatform":0,"minConditionPlatform":18,"name":"nfcstate","packages":["plugins"],"priceType":1,"remote":null,"source":0,"title":"NFC","type":1},{"description":"GPS 设置","maxActionPlatform":2147483647,"maxConditionPlatform":2147483647,"minActionPlatform":0,"minConditionPlatform":0,"name":"gps","packages":["plugins"],"priceType":1,"remote":null,"source":0,"title":"GPS","type":1},{"description":"根据当前活动（如步行，骑自行车或驾驶）切换状态。","maxActionPlatform":2147483647,"maxConditionPlatform":2147483647,"minActionPlatform":0,"minConditionPlatform":0,"name":"activity","packages":["plugins"],"priceType":1,"remote":null,"source":0,"title":"活动","type":1},{"description":"检测接近设备的物体","maxActionPlatform":2147483647,"maxConditionPlatform":2147483647,"minActionPlatform":0,"minConditionPlatform":0,"name":"proximity","packages":["plugins"],"priceType":1,"remote":null,"source":0,"title":"接近传感器","type":1},{"description":"通话状态","maxActionPlatform":2147483647,"maxConditionPlatform":2147483647,"minActionPlatform":0,"minConditionPlatform":0,"name":"callstate","packages":["plugins"],"priceType":1,"remote":null,"source":0,"title":"通话状态","type":1},{"description":"移动数据网络连接设置","maxActionPlatform":19,"maxConditionPlatform":2147483647,"minActionPlatform":0,"minConditionPlatform":0,"name":"mobiledata","packages":["plugins"],"priceType":0,"remote":null,"source":0,"title":"移动数据网络连接","type":16},{"description":"飞行模式设置","maxActionPlatform":2147483647,"maxConditionPlatform":2147483647,"minActionPlatform":23,"minConditionPlatform":0,"name":"flightmode","packages":["plugins"],"priceType":0,"remote":null,"source":0,"title":"飞行模式","type":16},{"description":"省电模式设置","maxActionPlatform":2147483647,"maxConditionPlatform":2147483647,"minActionPlatform":21,"minConditionPlatform":21,"name":"powersave","packages":["plugins"],"priceType":0,"remote":null,"source":0,"title":"省电模式","type":16},{"description":"铃声设置","maxActionPlatform":2147483647,"maxConditionPlatform":2147483647,"minActionPlatform":0,"minConditionPlatform":0,"name":"ringtone","packages":["plugins"],"priceType":1,"remote":null,"source":0,"title":"铃声","type":16},{"description":"通知音量设置","maxActionPlatform":2147483647,"maxConditionPlatform":2147483647,"minActionPlatform":0,"minConditionPlatform":0,"name":"volumealarm","packages":["plugins"],"priceType":1,"remote":null,"source":0,"title":"通知音量","type":16},{"description":"对不同联系人的来电和短信使用特别的音量","maxActionPlatform":2147483647,"maxConditionPlatform":2147483647,"minActionPlatform":0,"minConditionPlatform":0,"name":"volumecontact","packages":["plugins"],"priceType":1,"remote":null,"source":0,"title":"联系人音量","type":16},{"description":"媒体音量设置","maxActionPlatform":2147483647,"maxConditionPlatform":2147483647,"minActionPlatform":0,"minConditionPlatform":0,"name":"volumemedia","packages":["plugins"],"priceType":1,"remote":null,"source":0,"title":"媒体音量","type":16},{"description":"通知音量设置","maxActionPlatform":2147483647,"maxConditionPlatform":2147483647,"minActionPlatform":0,"minConditionPlatform":0,"name":"volumenotifications","packages":["plugins"],"priceType":1,"remote":null,"source":0,"title":"通知音量","type":16},{"description":"铃声音量设置","maxActionPlatform":2147483647,"maxConditionPlatform":2147483647,"minActionPlatform":0,"minConditionPlatform":0,"name":"volumeringtone","packages":["plugins"],"priceType":1,"remote":null,"source":0,"title":"铃声音量","type":16},{"description":"语音通话音量设置","maxActionPlatform":2147483647,"maxConditionPlatform":2147483647,"minActionPlatform":0,"minConditionPlatform":0,"name":"volumevoicecall","packages":["plugins"],"priceType":1,"remote":null,"source":0,"title":"语音通话音量","type":16},{"description":"启用勿扰模式","maxActionPlatform":2147483647,"maxConditionPlatform":2147483647,"minActionPlatform":23,"minConditionPlatform":23,"name":"donotdisturb","packages":["plugins"],"priceType":1,"remote":null,"source":0,"title":"勿扰模式","type":16},{"description":"屏幕自动旋转设置","maxActionPlatform":2147483647,"maxConditionPlatform":2147483647,"minActionPlatform":0,"minConditionPlatform":0,"name":"screenrotation","packages":["plugins"],"priceType":1,"remote":null,"source":0,"title":"屏幕旋转","type":16},{"description":"熄屏时间设置","maxActionPlatform":2147483647,"maxConditionPlatform":2147483647,"minActionPlatform":0,"minConditionPlatform":0,"name":"screentimeout","packages":["plugins"],"priceType":1,"remote":null,"source":0,"title":"熄屏时间","type":16},{"description":"账户同步设置","maxActionPlatform":2147483647,"maxConditionPlatform":2147483647,"minActionPlatform":0,"minConditionPlatform":0,"name":"sync","packages":["plugins"],"priceType":1,"remote":null,"source":0,"title":"同步","type":16},{"description":"网络分享 (热点) 设置","maxActionPlatform":2147483647,"maxConditionPlatform":2147483647,"minActionPlatform":0,"minConditionPlatform":0,"name":"tethering","packages":["plugins"],"priceType":0,"remote":null,"source":0,"title":"网络分享","type":16},{"description":"系统壁纸设置","maxActionPlatform":2147483647,"maxConditionPlatform":2147483647,"minActionPlatform":0,"minConditionPlatform":0,"name":"wallpaper","packages":["plugins"],"priceType":1,"remote":null,"source":0,"title":"壁纸","type":2},{"description":"记录状态更改日志","maxActionPlatform":2147483647,"maxConditionPlatform":2147483647,"minActionPlatform":0,"minConditionPlatform":0,"name":"logging","packages":["plugins"],"priceType":1,"remote":null,"source":0,"title":"日志","type":2},{"description":"使用短信回复未接电话","maxActionPlatform":2147483647,"maxConditionPlatform":2147483647,"minActionPlatform":0,"minConditionPlatform":0,"name":"smsreply","packages":["plugins"],"priceType":0,"remote":null,"source":0,"title":"短信回复","type":2},{"description":"发送短信到选择的联系人","maxActionPlatform":2147483647,"maxConditionPlatform":2147483647,"minActionPlatform":0,"minConditionPlatform":0,"name":"smssend","packages":["plugins"],"priceType":0,"remote":null,"source":0,"title":"发送短信","type":2}],"version":254}}