{"checksum":"47DEQpj8HBSa+/TImW+5JCeuQeRkm5NMpJWZG3hSuFU=","payload":{"features":[{"description":"***","maxPlatform":2147483647,"minPlatform":0,"name":"plugins","priceType":1,"title":"Get all plugins!!","type":4},{"description":"Расширяет условия Календаря поиском по ключевому слову и выбором календаря","maxActionPlatform":2147483647,"maxConditionPlatform":2147483647,"minActionPlatform":0,"minConditionPlatform":0,"name":"calendarpro","packages":["plugins"],"priceType":1,"remote":null,"source":0,"title":"Профессиональный календарь","type":1},{"description":"Extends the WiFi condition with address based search and scan interval selection","maxActionPlatform":2147483647,"maxConditionPlatform":2147483647,"minActionPlatform":0,"minConditionPlatform":0,"name":"wlanscanpro","packages":["plugins"],"priceType":1,"remote":null,"source":0,"title":"WiFi Pro","type":1},{"description":"Extends the Bluetooth condition with address based search and scan interval selection","maxActionPlatform":2147483647,"maxConditionPlatform":2147483647,"minActionPlatform":0,"minConditionPlatform":0,"name":"btscanpro","packages":["plugins"],"priceType":1,"remote":null,"source":0,"title":"Bluetooth Pro","type":1},{"description":"Display on/off state","maxActionPlatform":2147483647,"maxConditionPlatform":2147483647,"minActionPlatform":0,"minConditionPlatform":0,"name":"display","packages":["plugins"],"priceType":1,"remote":null,"source":0,"title":"Display","type":1},{"description":"Use NFC tags to toggle situations","maxActionPlatform":2147483647,"maxConditionPlatform":2147483647,"minActionPlatform":0,"minConditionPlatform":0,"name":"nfc","packages":["plugins"],"priceType":1,"remote":null,"source":0,"title":"NFC Tag","type":1},{"description":"NFC setting","maxActionPlatform":2147483647,"maxConditionPlatform":2147483647,"minActionPlatform":0,"minConditionPlatform":18,"name":"nfcstate","packages":["plugins"],"priceType":1,"remote":null,"source":0,"title":"NFC","type":1},{"description":"GPS setting","maxActionPlatform":2147483647,"maxConditionPlatform":2147483647,"minActionPlatform":0,"minConditionPlatform":0,"name":"gps","packages":["plugins"],"priceType":1,"remote":null,"source":0,"title":"GPS","type":1},{"description":"Change situation based on current activity (like walking, cycling or driving).","maxActionPlatform":2147483647,"maxConditionPlatform":2147483647,"minActionPlatform":0,"minConditionPlatform":0,"name":"activity","packages":["plugins"],"priceType":1,"remote":null,"source":0,"title":"Activity","type":1},{"description":"Detect objects being close to the device","maxActionPlatform":2147483647,"maxConditionPlatform":2147483647,"minActionPlatform":0,"minConditionPlatform":0,"name":"proximity","packages":["plugins"],"priceType":1,"remote":null,"source":0,"title":"Proximity Sensor","type":1},{"description":"Current call state","maxActionPlatform":2147483647,"maxConditionPlatform":2147483647,"minActionPlatform":0,"minConditionPlatform":0,"name":"callstate","packages":["plugins"],"priceType":1,"remote":null,"source":0,"title":"Call State","type":1},{"description":"There are missed calls in the call log","maxActionPlatform":2147483647,"maxConditionPlatform":2147483647,"minActionPlatform":0,"minConditionPlatform":0,"name":"missedcalls","packages":["plugins"],"priceType":1,"remote":null,"source":0,"title":"Missed Calls","type":1},{"description":"There are unread SMS messages","maxActionPlatform":2147483647,"maxConditionPlatform":2147483647,"minActionPlatform":0,"minConditionPlatform":0,"name":"missedsms","packages":["plugins"],"priceType":1,"remote":null,"source":0,"title":"Unread SMS Messages","type":1},{"description":"Переключатель мобильных данных","maxActionPlatform":19,"maxConditionPlatform":2147483647,"minActionPlatform":0,"minConditionPlatform":0,"name":"mobiledata","packages":["plugins"],"priceType":0,"remote":null,"source":0,"title":"Мобильные данные","type":16},{"description":"Переключатель автономного режима","maxActionPlatform":2147483647,"maxConditionPlatform":2147483647,"minActionPlatform":23,"minConditionPlatform":0,"name":"flightmode","packages":["plugins"],"priceType":0,"remote":null,"source":0,"title":"Автономный режим","type":16},{"description":"Battery Saver setting","maxActionPlatform":2147483647,"maxConditionPlatform":2147483647,"minActionPlatform":21,"minConditionPlatform":21,"name":"powersave","packages":["plugins"],"priceType":0,"remote":null,"source":0,"title":"Battery Saver","type":16},{"description":"Ringtone setting","maxActionPlatform":2147483647,"maxConditionPlatform":2147483647,"minActionPlatform":0,"minConditionPlatform":0,"name":"ringtone","packages":["plugins"],"priceType":1,"remote":null,"source":0,"title":"Ringtone","type":16},{"description":"Alarm volume setting","maxActionPlatform":2147483647,"maxConditionPlatform":2147483647,"minActionPlatform":0,"minConditionPlatform":0,"name":"volumealarm","packages":["plugins"],"priceType":1,"remote":null,"source":0,"title":"Alarm Volume","type":16},{"description":"Contact specific volume for incoming calls and SMS","maxActionPlatform":2147483647,"maxConditionPlatform":2147483647,"minActionPlatform":0,"minConditionPlatform":0,"name":"volumecontact","packages":["plugins"],"priceType":1,"remote":null,"source":0,"title":"Contact Volume","type":16},{"description":"Настраивает громкость медиа","maxActionPlatform":2147483647,"maxConditionPlatform":2147483647,"minActionPlatform":0,"minConditionPlatform":0,"name":"volumemedia","packages":["plugins"],"priceType":1,"remote":null,"source":0,"title":"Громкость медиа","type":16},{"description":"Настраивает громкость оповещений","maxActionPlatform":2147483647,"maxConditionPlatform":2147483647,"minActionPlatform":0,"minConditionPlatform":0,"name":"volumenotifications","packages":["plugins"],"priceType":1,"remote":null,"source":0,"title":"Громкость оповещений","type":16},{"description":"Настраивает громкость звонка","maxActionPlatform":2147483647,"maxConditionPlatform":2147483647,"minActionPlatform":0,"minConditionPlatform":0,"name":"volumeringtone","packages":["plugins"],"priceType":1,"remote":null,"source":0,"title":"Громкость звонка","type":16},{"description":"Voice Call Volume setting","maxActionPlatform":2147483647,"maxConditionPlatform":2147483647,"minActionPlatform":0,"minConditionPlatform":0,"name":"volumevoicecall","packages":["plugins"],"priceType":1,"remote":null,"source":0,"title":"Voice Call Volume","type":16},{"description":"Do Not Disturb setting","maxActionPlatform":2147483647,"maxConditionPlatform":2147483647,"minActionPlatform":23,"minConditionPlatform":23,"name":"donotdisturb","packages":["plugins"],"priceType":1,"remote":null,"source":0,"title":"Do Not Disturb","type":16},{"description":"Переключатель автоматического поворота экрана","maxActionPlatform":2147483647,"maxConditionPlatform":2147483647,"minActionPlatform":0,"minConditionPlatform":0,"name":"screenrotation","packages":["plugins"],"priceType":1,"remote":null,"source":0,"title":"Поворот экрана","type":16},{"description":"Таймаут экрана","maxActionPlatform":2147483647,"maxConditionPlatform":2147483647,"minActionPlatform":0,"minConditionPlatform":0,"name":"screentimeout","packages":["plugins"],"priceType":1,"remote":null,"source":0,"title":"Таймаут экрана","type":16},{"description":"Переключатель синхронизации","maxActionPlatform":2147483647,"maxConditionPlatform":2147483647,"minActionPlatform":0,"minConditionPlatform":0,"name":"sync","packages":["plugins"],"priceType":1,"remote":null,"source":0,"title":"Синхронизация","type":16},{"description":"Internet sharing (hotspot) setting","maxActionPlatform":2147483647,"maxConditionPlatform":2147483647,"minActionPlatform":0,"minConditionPlatform":0,"name":"tethering","packages":["plugins"],"priceType":0,"remote":null,"source":0,"title":"Internet Sharing","type":16},{"description":"System wallpaper setting","maxActionPlatform":2147483647,"maxConditionPlatform":2147483647,"minActionPlatform":0,"minConditionPlatform":0,"name":"wallpaper","packages":["plugins"],"priceType":1,"remote":null,"source":0,"title":"Wallpaper","type":2},{"description":"Keep log of situation changes","maxActionPlatform":2147483647,"maxConditionPlatform":2147483647,"minActionPlatform":0,"minConditionPlatform":0,"name":"logging","packages":["plugins"],"priceType":1,"remote":null,"source":0,"title":"Log","type":2},{"description":"ќтвечает на пропущенные звонки SMS-сообщением","maxActionPlatform":2147483647,"maxConditionPlatform":2147483647,"minActionPlatform":0,"minConditionPlatform":0,"name":"smsreply","packages":["plugins"],"priceType":0,"remote":null,"source":0,"title":"SMS-ответ","type":2},{"description":"Отправляет SMS сообщение выбранному контакту","maxActionPlatform":2147483647,"maxConditionPlatform":2147483647,"minActionPlatform":0,"minConditionPlatform":0,"name":"smssend","packages":["plugins"],"priceType":0,"remote":null,"source":0,"title":"Отправка SMS","type":2}],"version":264}}