{"checksum":"47DEQpj8HBSa+/TImW+5JCeuQeRkm5NMpJWZG3hSuFU=","payload":{"features":[{"description":"Extends the Bluetooth condition with address based search and scan interval selection","maxActionPlatform":2147483647,"maxConditionPlatform":2147483647,"minActionPlatform":0,"minConditionPlatform":0,"name":"btscanpro","packages":["plugins"],"priceType":0,"remote":"u0lXU2C/qb6xknDYGJF7m4xZ4lz0JyCdflMSmQivLx0=","source":1,"title":"Bluetooth Pro","type":1},{"description":"Extends the WiFi condition with address based search and scan interval selection","maxActionPlatform":2147483647,"maxConditionPlatform":2147483647,"minActionPlatform":0,"minConditionPlatform":0,"name":"wlanscanpro","packages":["plugins"],"priceType":0,"remote":"xM1fQ9Y0thpCscJ/YMN2moBB2phf3S0D5RuEupugkKc=","source":1,"title":"WiFi Pro","type":1},{"description":"Critère de positionnement utilisant la meilleure méthode de localisation","maxActionPlatform":2147483647,"maxConditionPlatform":2147483647,"minActionPlatform":0,"minConditionPlatform":0,"name":"location","packages":["plugins"],"priceType":0,"remote":"nj9n8yAQRbEqoi18PJ9olgUrTz8XthFMvpe68kr3jx0=","source":1,"title":"Localisation","type":1},{"description":"Display on/off state","maxActionPlatform":2147483647,"maxConditionPlatform":2147483647,"minActionPlatform":0,"minConditionPlatform":0,"name":"display","packages":["plugins"],"priceType":0,"remote":"nxDAWZE067W8f/rLcE0vC60HJzkm+FDT4kbHyyBzabI=","source":1,"title":"Display","type":1},{"description":"GPS setting","maxActionPlatform":2147483647,"maxConditionPlatform":2147483647,"minActionPlatform":0,"minConditionPlatform":0,"name":"gps","packages":["plugins"],"priceType":0,"remote":"7pRPwGGCImscn9i5EWmnwUBzeeSjzeHeB8hUHwFtpcM=","source":1,"title":"GPS","type":1},{"description":"Bouton de données mobiles","maxActionPlatform":2147483647,"maxConditionPlatform":2147483647,"minActionPlatform":0,"minConditionPlatform":0,"name":"mobiledata","packages":["plugins"],"priceType":0,"remote":"UgUSs+Fitc4WIds58vPwKfGXpPtETyW8GRN8diXl78A=","source":1,"title":"Données Mobiles","type":16},{"description":"Bouton de réseau mobile","maxActionPlatform":2147483647,"maxConditionPlatform":2147483647,"minActionPlatform":0,"minConditionPlatform":0,"name":"mobilenetwork","packages":["plugins"],"priceType":0,"remote":"aT31WPPTUG1bMqONT3QoZrXtyfCeCOqkz287xYQ+M98=","source":1,"title":"Réseau Mobile","type":16},{"description":"Bouton de mode avion","maxActionPlatform":2147483647,"maxConditionPlatform":2147483647,"minActionPlatform":0,"minConditionPlatform":0,"name":"flightmode","packages":["plugins"],"priceType":0,"remote":"Y5WGCf/t39TdNofuj0YvEV+JwwEz7bIFgNUVy6ib4ZY=","source":1,"title":"Mode Avion","type":16},{"description":"Ringtone setting","maxActionPlatform":2147483647,"maxConditionPlatform":2147483647,"minActionPlatform":0,"minConditionPlatform":0,"name":"ringtone","packages":["plugins"],"priceType":0,"remote":"OVpN+HuAQbLrWVNo97cj8xPwzbe3IkH9ZJkO+IVQPBA=","source":1,"title":"Ringtone","type":16},{"description":"Vibration setting","maxActionPlatform":2147483647,"maxConditionPlatform":2147483647,"minActionPlatform":0,"minConditionPlatform":0,"name":"vibration","packages":["plugins"],"priceType":0,"remote":"zjJGyU1yJlcImdhsExizuSVwjJtOmmSMyeKjzmX3RBQ=","source":1,"title":"Vibration","type":16},{"description":"Changeur d'ambiance","maxActionPlatform":2147483647,"maxConditionPlatform":2147483647,"minActionPlatform":0,"minConditionPlatform":0,"name":"ambience","packages":["plugins"],"priceType":0,"remote":"XhwBHsH/4RSvz4g9tNrvS2ZBuGvDAwuvOVGBQSueCGg=","source":1,"title":"Ambiance","type":16},{"description":"Internet sharing (hotspot) setting","maxActionPlatform":2147483647,"maxConditionPlatform":2147483647,"minActionPlatform":0,"minConditionPlatform":0,"name":"tethering","packages":["plugins"],"priceType":0,"remote":"kKcguvmB4fuAtD6aSK+QEybs+3j4wJU/f0qiBmYhbD8=","source":1,"title":"Internet Sharing","type":16},{"description":"Run any custom command","maxActionPlatform":2147483647,"maxConditionPlatform":2147483647,"minActionPlatform":0,"minConditionPlatform":0,"name":"command","packages":["plugins"],"priceType":0,"remote":"Nj1bLJu7K4A7WFKM/h+6lAckI5tSFy5SwQYcZTYojpQ=","source":1,"title":"Command","type":2},{"description":"Keep log of situation changes","maxActionPlatform":2147483647,"maxConditionPlatform":2147483647,"minActionPlatform":0,"minConditionPlatform":0,"name":"logging","packages":["plugins"],"priceType":0,"remote":"HYlhIo69jrE19fNdziqn4DzkJHYGQt+j22tk7mHw9D0=","source":1,"title":"Log","type":2},{"description":"Change watchface on your smartwatch. Compatible with Rockpool app.","maxActionPlatform":2147483647,"maxConditionPlatform":2147483647,"minActionPlatform":0,"minConditionPlatform":0,"name":"watchface","packages":["plugins"],"priceType":0,"remote":"v0/mhF6/n67NPLSnZX2lyqUjfnqTkmO+2nd2Rg4MlGY=","source":1,"title":"Watchface","type":2}],"version":132}}