{"checksum":"47DEQpj8HBSa+/TImW+5JCeuQeRkm5NMpJWZG3hSuFU=","payload":{"features":[{"description":"Extienda la condición WiFi con búsqueda basada en direcciones y selección de intervalo de escaneo","maxActionPlatform":2147483647,"maxConditionPlatform":2147483647,"minActionPlatform":0,"minConditionPlatform":0,"name":"wlanscanpro","packages":["plugins"],"priceType":0,"remote":"7nXWtzlqt/NBrfwlHYQn8Dm/QU8CsxY5QFIAOD540Ic=","source":1,"title":"WiFi Pro","type":1},{"description":"Extienda la condición Bluetooth con búsqueda basada en direcciones y selección de intervalo de escaneo","maxActionPlatform":2147483647,"maxConditionPlatform":2147483647,"minActionPlatform":0,"minConditionPlatform":0,"name":"btscanpro","packages":["plugins"],"priceType":0,"remote":"UtlORVnr1K2aKvC1ZgoQHhR0P1UECyhJQY2Q+qjWIY8=","source":1,"title":"Bluetooth Pro","type":1},{"description":"Condición de ubicación usando el mejor método de posicionamiento disponible","maxActionPlatform":2147483647,"maxConditionPlatform":2147483647,"minActionPlatform":0,"minConditionPlatform":0,"name":"location","packages":["plugins"],"priceType":0,"remote":"dD7Q0FwC68E2K+iOtErXPW4rki6lup1TpdSGx3qIeSA=","source":1,"title":"Ubicación","type":1},{"description":"Estado de pantalla encendida/apagada","maxActionPlatform":2147483647,"maxConditionPlatform":2147483647,"minActionPlatform":0,"minConditionPlatform":0,"name":"display","packages":["plugins"],"priceType":0,"remote":"btsaFt6l7Q7BOEOY9jIq5cCm/31a61FXZESS9BhL048=","source":1,"title":"Pantalla","type":1},{"description":"Ajuste GPS","maxActionPlatform":2147483647,"maxConditionPlatform":2147483647,"minActionPlatform":0,"minConditionPlatform":0,"name":"gps","packages":["plugins"],"priceType":0,"remote":"il/Pmdr+cmEmH6Rgx99JR088v5PRw7df6+BWPon61jU=","source":1,"title":"GPS","type":1},{"description":"Detectar objetos cercanos al dispositivo","maxActionPlatform":2147483647,"maxConditionPlatform":2147483647,"minActionPlatform":0,"minConditionPlatform":0,"name":"proximity","packages":["plugins"],"priceType":0,"remote":"VSJWn3V93cdbBWlvW9tLZ3a69zmP0aiNXIQz5SWZqXk=","source":1,"title":"Sensor de proximidiad","type":1},{"description":"Ajuste de Datos móviles","maxActionPlatform":2147483647,"maxConditionPlatform":2147483647,"minActionPlatform":0,"minConditionPlatform":0,"name":"mobiledata","packages":["plugins"],"priceType":0,"remote":"lnTmolOJnWfQHnL5/zht6HOm3gsEQ8J8dj/LRXT51xM=","source":1,"title":"Datos móviles","type":16},{"description":"Ajuster para red móvil","maxActionPlatform":2147483647,"maxConditionPlatform":2147483647,"minActionPlatform":0,"minConditionPlatform":0,"name":"mobilenetwork","packages":["plugins"],"priceType":0,"remote":"9A3E1cM5rq3a+A4Po7fs6GAI7I6z5GLEHVl0MFkplVE=","source":1,"title":"Red móvil","type":16},{"description":"Ajuste Modo Avión","maxActionPlatform":2147483647,"maxConditionPlatform":2147483647,"minActionPlatform":0,"minConditionPlatform":0,"name":"flightmode","packages":["plugins"],"priceType":0,"remote":"IQ7o/ucyI6oOr1xifrdqvvVhzkyzse7NFu4j/HTy4xQ=","source":1,"title":"Modo Avión","type":16},{"description":"Ajuste de tono de llamada","maxActionPlatform":2147483647,"maxConditionPlatform":2147483647,"minActionPlatform":0,"minConditionPlatform":0,"name":"ringtone","packages":["plugins"],"priceType":0,"remote":"embnhQqPyazmyIzriA5tNkEL0I2VA6/o1S2lzsCsa24=","source":1,"title":"Tono de llamada","type":16},{"description":"Ajustes de la vibración","maxActionPlatform":2147483647,"maxConditionPlatform":2147483647,"minActionPlatform":0,"minConditionPlatform":0,"name":"vibration","packages":["plugins"],"priceType":0,"remote":"Xal8LmuB0i1LntAK49wYm28waXjv6YNe9Z80QYFTCbk=","source":1,"title":"Vibración","type":16},{"description":"Ajuste der ambiente","maxActionPlatform":2147483647,"maxConditionPlatform":2147483647,"minActionPlatform":0,"minConditionPlatform":0,"name":"ambience","packages":["plugins"],"priceType":0,"remote":"/EXIhF7AwbTq94e9PHgsSkGQma4Pbjvz548secZRys8=","source":1,"title":"Ambiente","type":16},{"description":"Ajuste para compartir Internet (punto de acceso)","maxActionPlatform":2147483647,"maxConditionPlatform":2147483647,"minActionPlatform":0,"minConditionPlatform":0,"name":"tethering","packages":["plugins"],"priceType":0,"remote":"EyXj37KFzdtZHVj0fp3Bos0mAGR8lotXZSPuOJlkkZk=","source":1,"title":"Compartir Internet","type":16},{"description":"Ejecutar cualquier comando personalizado","maxActionPlatform":2147483647,"maxConditionPlatform":2147483647,"minActionPlatform":0,"minConditionPlatform":0,"name":"command","packages":["plugins"],"priceType":0,"remote":"IkSrjUqtcwQXub0vSEZjGLy6J/o4Orr1Vh+zU4x25s4=","source":1,"title":"Comando","type":2},{"description":"Guarde un registro de los cambios de situación","maxActionPlatform":2147483647,"maxConditionPlatform":2147483647,"minActionPlatform":0,"minConditionPlatform":0,"name":"logging","packages":["plugins"],"priceType":0,"remote":"2w41hSDR3buqoTsm94tmWJwc4/JPHJCeh/eWmSeZ+Mw=","source":1,"title":"Registro","type":2},{"description":"Cambia la pantalla en su smartwatch. Compatible con la app Rockpool.","maxActionPlatform":2147483647,"maxConditionPlatform":2147483647,"minActionPlatform":0,"minConditionPlatform":0,"name":"watchface","packages":["plugins"],"priceType":0,"remote":"5jxJ+rD4WRO79uDd2Ov+XMzWquP2dZlkiVtYUw0cK0M=","source":1,"title":"Pantalla de reloj","type":2}],"version":220}}